retro_pkg_test/__init__.py
retro_pkg_test/hello.py
retro_pkg_test-3.1415.dist-info/LICENSE
retro_pkg_test-3.1415.dist-info/METADATA
retro_pkg_test-3.1415.dist-info/WHEEL
retro_pkg_test-3.1415.dist-info/top_level.txt
retro_pkg_test-3.1415.dist-info/RECORD
